openBOS/__init__.py
openBOS/culculate_refractiveindex.py
openBOS/evaluation.py
openBOS/reconstruction.py
openBOS/reconstruction_utils.py
openBOS/shift.py
openBOS/shift_utils.py
openBOS/utils.py
openBOS-0.0.45.dist-info/LICENSE
openBOS-0.0.45.dist-info/METADATA
openBOS-0.0.45.dist-info/WHEEL
openBOS-0.0.45.dist-info/top_level.txt
openBOS-0.0.45.dist-info/RECORD
