Metadata-Version: 2.1
Name: openBOS
Version: 0.0.45
Summary: the library of Background Oriented Schlieren
Home-page: https://github.com/ogayuuki0202/openBOS
Download-URL: https://github.com/ogayuuki0202/openBOS
Author: Yuuki Ogasawara
Author-email: yukiogasawara.research@gmail.com
Maintainer: Yuuki Ogasawara
Maintainer-email: yukiogasawara.research@gmail.com
License: GNU GENERAL PUBLIC LICENSE,
Classifier: Intended Audience :: Science/Research
Classifier: License :: OSI Approved :: GNU Lesser General Public License v3 (LGPLv3)
Classifier: Programming Language :: Python :: 3
Classifier: Programming Language :: Python :: 3.6
Classifier: Programming Language :: Python :: 3.7
Classifier: Programming Language :: Python :: 3.8
Classifier: Programming Language :: Python :: 3.9
Classifier: Programming Language :: Python :: 3 :: Only
Classifier: Topic :: Scientific/Engineering
Classifier: Topic :: Scientific/Engineering :: Visualization
Classifier: Topic :: Multimedia :: Graphics
Classifier: Framework :: Matplotlib
Requires-Python: >=3.6
License-File: LICENSE
Requires-Dist: matplotlib>=3.3.4
Requires-Dist: numpy<2.0,>=1.20.3
Requires-Dist: pandas>=1.2.4
Requires-Dist: scikit-image>=0.24.0
Requires-Dist: tqdm>=4.0
Requires-Dist: pillow>=6.0
Requires-Dist: scipy>=1.0
